linky_note/__init__.py
linky_note/adapters/__init__.py
linky_note/adapters/markdown/__init__.py
linky_note/adapters/markdown/factories.py
linky_note/adapters/markdown/marko_ext/__init__.py
linky_note/adapters/markdown/marko_ext/elements.py
linky_note/adapters/markdown/marko_ext/marko_builder.py
linky_note/adapters/markdown/marko_extractor.py
linky_note/adapters/markdown/marko_modifier.py
linky_note/adapters/markdown/marko_parser.py
linky_note/adapters/references_db/__init__.py
linky_note/adapters/references_db/factories.py
linky_note/adapters/references_db/query_builders.py
linky_note/adapters/references_db/tables.py
linky_note/common/__init__.py
linky_note/common/exceptions.py
linky_note/dto/__init__.py
linky_note/dto/dto.py
linky_note/entrypoints/__init__.py
linky_note/entrypoints/append_linked_references.py
linky_note/infrastructure/__init__.py
linky_note/infrastructure/db_connection.py
linky_note/interfaces/__init__.py
linky_note/interfaces/modifier.py
linky_note/interfaces/parser.py
linky_note/interfaces/reference_extractor.py
linky_note/interfaces/references_db.py
linky_note/interfaces/renderer.py
linky_note/py.typed
linky_note/usecases/__init__.py
linky_note/usecases/config.py
linky_note/usecases/modify.py
linky_note/usecases/parse.py
linky_note/usecases/read_references.py
linky_note/usecases/write.py
linky_note-0.4.4.dist-info/entry_points.txt
linky_note-0.4.4.dist-info/LICENSE
linky_note-0.4.4.dist-info/WHEEL
linky_note-0.4.4.dist-info/METADATA
linky_note-0.4.4.dist-info/RECORD
