Metadata-Version: 2.1
Name: linky-note
Version: 0.4.4
Summary: Awesome `linky-note` is a Python cli/package created with https://github.com/TezRomacH/python-package-template
Home-page: https://github.com/jb-delafosse/linky-note
License: MIT
Keywords: markdown,pre-commit,backlink,roamresearch
Author: jb-delafosse
Author-email: jean-baptiste@lumapps.com
Requires-Python: >=3.7,<4.0
Classifier: Development Status :: 3 - Alpha
Classifier: Intended Audience :: Developers
Classifier: License :: OSI Approved :: MIT License
Classifier: Operating System :: OS Independent
Classifier: Programming Language :: Python :: 3
Classifier: Programming Language :: Python :: 3.7
Classifier: Programming Language :: Python :: 3.8
Classifier: Programming Language :: Python :: 3.9
Classifier: Topic :: Software Development :: Libraries :: Python Modules
Classifier: Topic :: Text Processing :: Markup :: Markdown
Requires-Dist: PyYAML (>=5.4.1,<6.0.0)
Requires-Dist: importlib_metadata (>=1.6,<5.0); python_version < "3.8"
Requires-Dist: marko (>=0.10,<1.1)
Requires-Dist: rich (>=8,<10)
Requires-Dist: sqlalchemy (>=1.3.20,<2.0.0)
Requires-Dist: typer[all] (>=0.3.2,<0.4.0)
Project-URL: Repository, https://github.com/jb-delafosse/linky-note
